cobamp/__init__.py
cobamp/algorithms/__init__.py
cobamp/algorithms/kshortest.py
cobamp/analysis/__init__.py
cobamp/analysis/frequency.py
cobamp/analysis/graph.py
cobamp/analysis/plotting.py
cobamp/core/__init__.py
cobamp/core/cb_analysis.py
cobamp/core/linear_systems.py
cobamp/core/models.py
cobamp/core/optimization.py
cobamp/core/transformer.py
cobamp/gpr/__init__.py
cobamp/gpr/core.py
cobamp/gpr/integration.py
cobamp/nullspace/__init__.py
cobamp/nullspace/nullspace.py
cobamp/nullspace/subset_reduction.py
cobamp/utilities/__init__.py
cobamp/utilities/context.py
cobamp/utilities/file_io.py
cobamp/utilities/hash.py
cobamp/utilities/linear_system_diagnostics.py
cobamp/utilities/parallel.py
cobamp/utilities/postfix_expressions.py
cobamp/utilities/printing.py
cobamp/utilities/property_management.py
cobamp/utilities/set.py
cobamp/utilities/test.py
cobamp/utilities/tree.py
cobamp/wrappers/__init__.py
cobamp/wrappers/cobamp.py
cobamp/wrappers/cobra.py
cobamp/wrappers/core.py
cobamp/wrappers/external_wrappers.py
cobamp/wrappers/framed.py
cobamp/wrappers/method_wrappers.py
cobamp-0.2.2.dist-info/LICENSE.txt
cobamp-0.2.2.dist-info/METADATA
cobamp-0.2.2.dist-info/WHEEL
cobamp-0.2.2.dist-info/notice.txt
cobamp-0.2.2.dist-info/top_level.txt
cobamp-0.2.2.dist-info/RECORD
