Metadata-Version: 2.1
Name: cobamp
Version: 0.2.2
Summary: cobamp - pathway analysis methods for genome-scale metabolic models
Home-page: https://github.com/BioSystemsUM/cobamp
Author: Vítor Vieira
Author-email: vvieira@ceb.uminho.pt
License: GNU General Public License v3.0
Keywords: pathway analysis metabolic model
Platform: UNKNOWN
Classifier: Development Status :: 4 - Beta
Classifier: Topic :: Scientific/Engineering :: Bio-Informatics
Classifier: Intended Audience :: Science/Research
Classifier: Programming Language :: Python :: 3.6
Classifier: License :: OSI Approved :: GNU General Public License v3 (GPLv3)
Classifier: Topic :: Software Development :: Libraries :: Python Modules
Requires-Dist: indexed (==1.2.1)
Requires-Dist: pandas (==1.3.5)
Requires-Dist: scipy (==1.7.3)
Requires-Dist: numpy (==1.21.6)
Requires-Dist: matplotlib (==3.5.2)
Requires-Dist: optlang (==1.5.2)
Requires-Dist: pathos (==0.2.9)
Requires-Dist: boolean.py (==3.8)
